{
    "update_interval": 2,
    "data_history_length": 300,
    "enable_smartctl": true,
    "smartctl_path": "",
    "web_port": 8070,
    "fans": [],
    "auto_detect": true,
    "log_level": "INFO",
    "enable_alerts": false,
    "alert_temp_cpu": 85.0,
    "alert_temp_disk": 60.0,
    "history_retention_days": 30,
    "alert_enabled": false,
    "alert_cooldown_minutes": 30,
    "smtp_host": "",
    "smtp_port": 465,
    "smtp_user": "",
    "smtp_password": "",
    "smtp_from": "",
    "smtp_to": "",
    "smtp_use_tls": true
}
